ddup/__init__.py
ddup/version.py
ddup/utils/__init__.py
ddup/utils/black.png
ddup/utils/chunks.py
ddup/utils/hash.py
ddup-0.0.7.data/data/ddup/utils/black.png
tools/__init__.py
tools/ddupsdk.py
ddup-0.0.7.dist-info/METADATA
ddup-0.0.7.dist-info/WHEEL
ddup-0.0.7.dist-info/entry_points.txt
ddup-0.0.7.dist-info/top_level.txt
ddup-0.0.7.dist-info/RECORD
