Metadata-Version: 2.1
Name: ddup
Version: 0.0.7
Summary: UNKNOWN
Home-page: UNKNOWN
License: UNKNOWN
Platform: UNKNOWN
Requires-Dist: h5py
Requires-Dist: imagehash
Requires-Dist: numpy
Requires-Dist: pillow
Requires-Dist: torch
